{"imageName": "1619416276673661_img", "imgHeight": 1089, "imgWidth": 2048, "icon": [{"location": [436, 611, 450, 625]}, {"location": [695, 158, 700, 172]}, {"location": [401, 135, 415, 149]}, {"location": [854, 35, 863, 43]}], "text": [{"location": [161, 508, 173, 520], "content": "\u5206"}, {"location": [819, 35, 831, 42], "content": "PE"}, {"location": [161, 356, 173, 369], "content": "\u5408"}, {"location": [907, 1012, 915, 1023], "content": "%"}, {"location": [751, 43, 767, 47], "content": "", "difficult": true}, {"location": [919, 158, 931, 168], "content": "59", "difficult": true}, {"location": [2016, 1067, 2036, 1077], "content": ":16"}, {"location": [1616, 722, 1808, 737], "content": "\u5370\u5ea6\u65b0\u589e\u65b0\u51a0\u75c5\u4f8b\u521b\u5168\u7403\u4e4b\u6700"}, {"location": [1616, 953, 1875, 968], "content": "\u5370\u5ea6\u75ab\u60c5\u6025\u5267\u6076\u5316\u7f8e\u56fd\u7ec8\u4e8e\"\u677e\u53e3\"\u652f\u63f4\uff1a"}, {"location": [891, 158, 916, 169], "content": "+9.7"}, {"location": [161, 452, 173, 465], "content": "\u6570", "difficult": true}, {"location": [161, 369, 173, 382], "content": "\u6392"}, {"location": [1690, 911, 1903, 926], "content": "\u6d77\u5916\u75ab\u60c5\u5347\u6e29\u5e02\u573a\u5b58\u5728\u4e0d\u786e\u5b9a\u6027"}, {"location": [1616, 323, 1741, 338], "content": "\u65e5\u672c\u4e1c\u4eac\u5927\u962a\u7b494\u5730"}, {"location": [1814, 722, 1974, 737], "content": "\u77ed\u671f\u5229\u597d\u68c0\u6d4b\u8bd5\u5242\u548c\u75ab..."}, {"location": [161, 439, 173, 452], "content": "\u6307"}, {"location": [1746, 323, 1880, 338], "content": "\u5b9e\u65bd\u7b2c\u4e09\u8f6e\u7d27\u6025\u72b6\u6001"}, {"location": [161, 521, 173, 534], "content": "\u6790", "difficult": true}, {"location": [432, 158, 454, 169], "content": "-0.1"}, {"location": [294, 1009, 310, 1026], "content": "\u745e"}, {"location": [905, 992, 915, 1003], "content": "%"}, {"location": [699, 155, 711, 171], "content": "\u4ebf"}, {"location": [1616, 806, 1704, 821], "content": "\u5370\u5ea6\u75ab\u60c5\u5931\u63a7"}, {"location": [774, 1012, 786, 1023], "content": "3%"}, {"location": [1980, 1067, 2016, 1077], "content": "13:51"}, {"location": [161, 342, 173, 355], "content": "\u7efc"}, {"location": [314, 1010, 342, 1024], "content": "\u533b\u7597"}, {"location": [1989, 1020, 2021, 1025], "content": "", "difficult": true}, {"location": [457, 158, 469, 168], "content": "59", "difficult": true}]}