{"imageName": "1619415787115700_img", "imgHeight": 1377, "imgWidth": 1920, "icon": [{"location": [1791, 2, 1795, 16]}, {"location": [12, 120, 20, 128]}, {"location": [1842, 78, 1851, 84]}], "text": [{"location": [854, 35, 863, 43], "content": "IP0"}, {"location": [4, 453, 16, 466], "content": "\u540d"}, {"location": [4, 522, 16, 534], "content": "\u80a1"}, {"location": [5, 83, 15, 95], "content": "\u9996", "difficult": true}, {"location": [4, 411, 16, 424], "content": "\u7efc"}, {"location": [4, 96, 16, 109], "content": "\u5458"}, {"location": [4, 646, 16, 659], "content": "\u5206"}, {"location": [5, 438, 16, 451], "content": "\u6392"}, {"location": [4, 425, 16, 438], "content": "\u5408", "difficult": true}, {"location": [4, 563, 16, 576], "content": "\u7ea7"}, {"location": [4, 659, 16, 672], "content": "\u6790", "difficult": true}, {"location": [4, 576, 16, 589], "content": "\u76d8"}, {"location": [4, 508, 16, 521], "content": "\u8bca"}, {"location": [819, 35, 831, 42], "content": "PE"}, {"location": [751, 43, 767, 47], "content": "", "difficult": true}]}