{"imageName": "1619417647731876_img", "imgHeight": 1440, "imgWidth": 2560, "icon": [{"location": [2287, 1, 2299, 9]}], "text": [{"location": [2531, 1421, 2537, 1431], "content": "2"}, {"location": [751, 43, 767, 47], "content": "", "difficult": true}, {"location": [819, 35, 831, 42], "content": "PE"}, {"location": [92, 1365, 107, 1371], "content": "", "difficult": true}, {"location": [189, 1365, 203, 1371], "content": "1C", "difficult": true}, {"location": [854, 35, 863, 43], "content": "IP0"}, {"location": [208, 1365, 223, 1371], "content": "", "difficult": true}, {"location": [56, 1365, 87, 1371], "content": "", "difficult": true}]}